{
  "2025": {
    "March": {
      "1": 1000,
      "2": 100,
      "3": 100,
      "4": 100,
      "8": 50,
      "9": 50,
      "10": 200,
      "12": 50
    },
    "April": {
      "3": 100,
      "4": 100,
      "7": 51,
      "8": 50,
      "10": 100,
      "13": 50,
      "18": 50,
      "20": 50,
      "21": 50,
      "22": 100,
      "23": 50,
      "24": 100,
      "25": 50,
      "33": 50,
      "35": 100,
      "44": 100,
      "47": 100,
      "54": 50,
      "57": 50,
      "59": 100,
      "60": 250,
      "61": 101,
      "62": 151,
      "64": 100,
      "67": 100,
      "69": 51,
      "70": 50,
      "75": 100,
      "76": 50,
      "77": 51,
      "79": 100,
      "84": 101,
      "85": 51,
      "88": 250,
      "90": 50,
      "92": 100,
      "93": 100,
      "94": 200
    }
  }
}